odoo/addons/delivery_cbl_picking_note_observations/README.rst
odoo/addons/delivery_cbl_picking_note_observations/__init__.py
odoo/addons/delivery_cbl_picking_note_observations/__manifest__.py
odoo/addons/delivery_cbl_picking_note_observations/models/__init__.py
odoo/addons/delivery_cbl_picking_note_observations/models/cbl_request.py
odoo/addons/delivery_cbl_picking_note_observations/models/delivery_carrier.py
odoo/addons/delivery_cbl_picking_note_observations/readme/CONFIGURE.md
odoo/addons/delivery_cbl_picking_note_observations/readme/CONTRIBUTORS.md
odoo/addons/delivery_cbl_picking_note_observations/readme/DESCRIPTION.md
odoo/addons/delivery_cbl_picking_note_observations/readme/ROADMAP.md
odoo/addons/delivery_cbl_picking_note_observations/readme/USAGE.md
odoo/addons/delivery_cbl_picking_note_observations/static/description/icon.png
odoo/addons/delivery_cbl_picking_note_observations/static/description/index.html
odoo/addons/delivery_cbl_picking_note_observations/tests/__init__.py
odoo/addons/delivery_cbl_picking_note_observations/tests/test_delivery_cbl_picking_note_observations.py
odoo/addons/delivery_cbl_picking_note_observations/views/delivery_carrier_views.xml
odoo_addon_delivery_cbl_picking_note_observations-17.0.1.0.0.1.dist-info/METADATA
odoo_addon_delivery_cbl_picking_note_observations-17.0.1.0.0.1.dist-info/WHEEL
odoo_addon_delivery_cbl_picking_note_observations-17.0.1.0.0.1.dist-info/top_level.txt
odoo_addon_delivery_cbl_picking_note_observations-17.0.1.0.0.1.dist-info/RECORD
