Metadata-Version: 2.1
Name: odoo-addon-delivery_cbl_picking_note_observations
Version: 17.0.1.0.0.1
Requires-Python: >=3.10
Requires-Dist: odoo-addon-delivery_cbl>=17.0dev,<17.1dev
Requires-Dist: odoo-addon-sale_stock_picking_note>=17.0dev,<17.1dev
Requires-Dist: odoo>=17.0a,<17.1dev
Summary: Send Observations to CBL Picking Deliveries with customer_note field
Home-page: https://github.com/sygel-technology/sy-delivery-carrier
License: AGPL-3
Author: Sygel, Odoo Community Association (OCA)
Author-email: support@odoo-community.org
Classifier: Programming Language :: Python
Classifier: Framework :: Odoo
Classifier: Framework :: Odoo :: 17.0
Classifier: License :: OSI Approved :: GNU Affero General Public License v3
